{
  "namespace": "music_lyric_player::render::config::line::normal",
  "file": "index.gen.h",
  "imports": [
    { "as": "common", "schema": "../../common/index.schema.json" },
    { "as": "main", "schema": "main/index.schema.json" }
  ],
  "items": [
    {
      "name": "Base",
      "comment": "Appearance shared by the main vocal line and its annotation sub-lines.",
      "fields": [
        {
          "name": "font",
          "nested": "common.FontConfig",
          "comment": "Font shared by every line."
        },
        {
          "name": "style",
          "nested": "common.StateStyleConfig",
          "comment": "Inactive and active styles shared by normal lyric lines."
        }
      ]
    },
    {
      "name": "Root",
      "comment": "Rendering settings of vocal lyric lines.",
      "fields": [
        {
          "name": "base",
          "nested": "Base",
          "comment": "Appearance shared by the main vocal line and its annotation sub-lines."
        },
        {
          "name": "main",
          "nested": "main.Root",
          "comment": "Rendering mode and settings of the main vocal content."
        }
      ]
    }
  ]
}
